report_generator/__init__.py
report_generator/conference.py
report_generator/config.py
report_generator/analyzer/__init__.py
report_generator/analyzer/generic.py
report_generator/analyzer/plotter.py
report_generator/cleaner/__init__.py
report_generator/cleaner/title.py
report_generator/controller/__init__.py
report_generator/controller/report_generator_cli.py
report_generator/data/default-2018.ini
report_generator/data/default-2019.ini
report_generator/data/default.ini
report_generator/data/general-plots-en-2019.yaml
report_generator/data/general-plots-en-2020.yaml
report_generator/data/generic.yaml
report_generator/exporter/__init__.py
report_generator/exporter/html.py
report_generator/exporter/data/Chart.min.js
report_generator/exporter/data/internal.html
report_generator/exporter/data/jquery-mobile.min.js
report_generator/exporter/data/jquery.min.js
report_generator/exporter/data/jquery.mobile.min.css
report_generator/exporter/data/sponsor.css
report_generator/exporter/data/sponsor.html
report_generator/io/__init__.py
report_generator/io/csv.py
report_generator/io/excel.py
report_generator/io/yaml.py
report_generator/opass/__init__.py
report_generator/opass/opass.py
report_generator/partner/__init__.py
report_generator/partner/sponsor.py
report_generator/ticket/__init__.py
report_generator/ticket/attendee.py
report_generator/viewer/__init__.py
report_generator/viewer/text.py
tests/__init__.py
tests/test_html_exporter.py
tests/test_sponsor.py
tests/test_title.py
tests/data/packages.yaml
tests/data/sponsors.yaml
tests/data/title-category.csv
pycontw_report_generator-1.5.2.dist-info/LICENSE
pycontw_report_generator-1.5.2.dist-info/METADATA
pycontw_report_generator-1.5.2.dist-info/WHEEL
pycontw_report_generator-1.5.2.dist-info/entry_points.txt
pycontw_report_generator-1.5.2.dist-info/top_level.txt
pycontw_report_generator-1.5.2.dist-info/RECORD
