Metadata-Version: 2.1
Name: pycontw-report-generator
Version: 1.5.2
Summary: PyCon TW post-event report generator. A cli command to generate PyCon TW post-event reports.
Home-page: https://github.com/pycontw/postevent-report-generator
Download-URL: https://github.com/pycontw/postevent-report-generator.git
Author: Taihsiang Ho (tai271828)
Author-email: tai271828@python.tw
License: BSD 3-Clause
Keywords: attendee,pycontw,post-event,report-generator
Platform: UNKNOWN
Classifier: Programming Language :: Python
License-File: LICENSE
Requires-Dist: pandas
Requires-Dist: seaborn
Requires-Dist: numpy
Requires-Dist: matplotlib
Requires-Dist: click (==7.0)
Requires-Dist: Pillow
Requires-Dist: Jinja2 (==2.10.3)
Requires-Dist: MarkupSafe (<=2.0.1)
Requires-Dist: PyYAML
